fundus/__init__.py
fundus/logging.py
fundus/py.typed
fundus/parser/__init__.py
fundus/parser/base_parser.py
fundus/parser/data.py
fundus/parser/utility.py
fundus/publishers/__init__.py
fundus/publishers/base_objects.py
fundus/publishers/at/__init__.py
fundus/publishers/at/derstandard.py
fundus/publishers/at/die_presse.py
fundus/publishers/at/kleine_zeitung.py
fundus/publishers/at/orf.py
fundus/publishers/at/salzburger_nachrichten.py
fundus/publishers/au/__init__.py
fundus/publishers/au/nine_news.py
fundus/publishers/au/west_australian.py
fundus/publishers/be/__init__.py
fundus/publishers/be/nieuwsblad.py
fundus/publishers/be/politico_eu.py
fundus/publishers/ca/__init__.py
fundus/publishers/ca/cbc_news.py
fundus/publishers/ca/globe_and_mail.py
fundus/publishers/ca/national_post.py
fundus/publishers/ch/__init__.py
fundus/publishers/ch/nzz.py
fundus/publishers/ch/srf.py
fundus/publishers/ch/ta.py
fundus/publishers/ch/zwanzig_minuten.py
fundus/publishers/cn/__init__.py
fundus/publishers/cn/people.py
fundus/publishers/cz/__init__.py
fundus/publishers/cz/seznamzpravy.py
fundus/publishers/de/__init__.py
fundus/publishers/de/berliner_zeitung.py
fundus/publishers/de/bild.py
fundus/publishers/de/boersenzeitung.py
fundus/publishers/de/br.py
fundus/publishers/de/business_insider_de.py
fundus/publishers/de/der_freitag.py
fundus/publishers/de/die_welt.py
fundus/publishers/de/die_zeit.py
fundus/publishers/de/dw.py
fundus/publishers/de/faz.py
fundus/publishers/de/focus.py
fundus/publishers/de/frankfurter_rundschau.py
fundus/publishers/de/freiepresse.py
fundus/publishers/de/funke.py
fundus/publishers/de/gamestar.py
fundus/publishers/de/golem.py
fundus/publishers/de/heise.py
fundus/publishers/de/hessenschau.py
fundus/publishers/de/junge_welt.py
fundus/publishers/de/kicker.py
fundus/publishers/de/klassegegenklasse.py
fundus/publishers/de/krautreporter.py
fundus/publishers/de/mdr.py
fundus/publishers/de/merkur.py
fundus/publishers/de/motorsport_magazin.py
fundus/publishers/de/mz.py
fundus-0.5.4.dist-info/LICENSE
fundus-0.5.4.dist-info/METADATA
fundus-0.5.4.dist-info/WHEEL
fundus-0.5.4.dist-info/top_level.txt
fundus-0.5.4.dist-info/RECORD
