Metadata-Version: 2.1
Name: fundus
Version: 0.5.4
Summary: A very simple news crawler
Author-email: Max Dallabetta <max.dallabetta@googlemail.com>
License: MIT
Project-URL: Repository, https://github.com/flairNLP/fundus
Keywords: web scraping, web crawling
Classifier: Programming Language :: Python :: 3
Classifier: License :: OSI Approved :: MIT License
Classifier: Operating System :: OS Independent
Classifier: Intended Audience :: Developers
Classifier: Intended Audience :: Education
Classifier: Intended Audience :: Science/Research
Requires-Python: >=3.8
License-File: LICENSE
Requires-Dist: python-dateutil<3,>=2.8
Requires-Dist: lxml<6,>=4.9
Requires-Dist: more-itertools<10,>=9.1
Requires-Dist: cssselect<2,>=1.1
Requires-Dist: feedparser<7,>=6.0
Requires-Dist: colorama<1,>=0.4
Requires-Dist: typing-extensions<5,>=4.6
Requires-Dist: langdetect<2,>=1.0
Requires-Dist: validators<1,>=0.24
Requires-Dist: requests<3,>=2.28
Requires-Dist: tqdm<5,>=4.66
Requires-Dist: fastwarc<1,>=0.14
Requires-Dist: chardet<6,>=5.2
Requires-Dist: dill<1,>=0.3
Requires-Dist: dict2xml<2,>=1.7.6
Requires-Dist: xmltodict<1,>=0.13.0
Requires-Dist: bidict<1,>=0.23
Provides-Extra: dev
Requires-Dist: pytest~=7.2.2; extra == "dev"
Requires-Dist: mypy==1.9.0; extra == "dev"
Requires-Dist: isort==5.12.0; extra == "dev"
Requires-Dist: black==23.1.0; extra == "dev"
Requires-Dist: types-lxml; extra == "dev"
Requires-Dist: types-python-dateutil<3,>=2.8; extra == "dev"
Requires-Dist: types-requests<3,>=2.28; extra == "dev"
Requires-Dist: types-colorama<1,>=0.4; extra == "dev"
